Metadata-Version: 2.1
Name: polyrot
Version: 0.0.1
Summary: polyrot computes polytropic models of rapidly rotating planets and stars
Home-page: https://github.com/dewberryjanosz/polyrot
Author: Janosz Dewberry
Author-email: jdewberry@cita.utoronto.ca
License: GPL-3.0-only
Classifier: Programming Language :: Python :: 3
Classifier: License :: OSI Approved :: GNU General Public License v3 (GPLv3)
Classifier: Operating System :: OS Independent
Requires-Python: >=3.6
License-File: LICENSE
